greenland/base/.gitignore
greenland/base/__init__.py
greenland/base/__version__.py
greenland/base/enums.py
greenland/base/py.typed
greenland/base/version.py
greenland_base-0.0.7.dist-info/METADATA
greenland_base-0.0.7.dist-info/WHEEL
greenland_base-0.0.7.dist-info/licenses/LICENSE.txt
greenland_base-0.0.7.dist-info/RECORD
