Metadata-Version: 2.3
Name: greenland-base
Version: 0.0.7
Summary: Basic types and algorithms for greenland
Project-URL: Homepage, https://codeberg.org/m-e-leypold/greenland-base
Project-URL: Documentation, https://codeberg.org/m-e-leypold/greenland-base#readme
Project-URL: Issues, https://codeberg.org/m-e-leypold/greenland-base/issues
Project-URL: Source, https://codeberg.org/m-e-leypold/greenland-base
Author: M E Leypold
Author-email: M E Leypold <pythonista-4sda212@m-e-leypold.de>
License: GPL-3.0-or-later
License-File: LICENSE.txt
Classifier: Development Status :: 4 - Beta
Classifier: Programming Language :: Python
Classifier: Programming Language :: Python :: 3.9
Classifier: Programming Language :: Python :: 3.10
Classifier: Programming Language :: Python :: 3.11
Classifier: Programming Language :: Python :: 3.12
Classifier: Programming Language :: Python :: Implementation :: CPython
Classifier: Programming Language :: Python :: Implementation :: PyPy
Requires-Python: >=3.8
Requires-Dist: docopt-ng
Requires-Dist: packaging
